MANIFEST.in
README.rst
setup.cfg
setup.py
pyrxnlp/__init__.py
pyrxnlp.egg-info/PKG-INFO
pyrxnlp.egg-info/SOURCES.txt
pyrxnlp.egg-info/dependency_links.txt
pyrxnlp.egg-info/requires.txt
pyrxnlp.egg-info/top_level.txt
pyrxnlp/api/__init__.py
pyrxnlp/api/cluster_sentences.py
pyrxnlp/api/text_similarity.py
pyrxnlp/api/util.py
pyrxnlp/corpora/__init__.py
pyrxnlp/corpora/clusteringsentences.txt
pyrxnlp/examples/__init__.py
pyrxnlp/examples/api_cluster_sentences.py
pyrxnlp/examples/api_text_similarity.py