Metadata-Version: 1.1
Name: pyrxnlp
Version: 0.1.4.8
Summary: Natural language processing tools
Home-page: https://github.com/RxNLP/pyrxnlp
Author: RxNLP
Author-email: kavita.ganesan@rxnlp.com
License: LICENSE
Download-URL: https://github.com/RxNLP/pyrxnlp/archive/0.1.4.tar.gz
Keywords: Sentence Clustering,Topics Extraction,Opinosis Summarization,Text Similarity
Platform: UNKNOWN
Classifier: Programming Language :: Python :: 3.5
Classifier: Programming Language :: Python :: 3.6
Classifier: Topic :: Scientific/Engineering :: Artificial Intelligence
Classifier: Topic :: Scientific/Engineering :: Information Analysis
Classifier: Topic :: Text Processing :: Linguistic
